clanvas/__init__.py
clanvas/clanvas.py
clanvas/completion.py
clanvas/config.py
clanvas/filesynchronizer.py
clanvas/interfaces.py
clanvas/lister.py
clanvas/outputter.py
clanvas/runner.py
clanvas/utils.py
clanvas-0.3.0.dist-info/LICENSE
clanvas-0.3.0.dist-info/METADATA
clanvas-0.3.0.dist-info/WHEEL
clanvas-0.3.0.dist-info/entry_points.txt
clanvas-0.3.0.dist-info/top_level.txt
clanvas-0.3.0.dist-info/RECORD
