Metadata-Version: 2.1
Name: clanvas
Version: 0.3.0
Summary: Command-line client for Canvas by Instructure
Home-page: https://github.com/marklalor/clanvas
Author: Mark Lalor
Author-email: markwlalor@gmail.com
License: MIT
Platform: UNKNOWN
Classifier: Development Status :: 3 - Alpha
Classifier: Environment :: Console
Classifier: Intended Audience :: Education
Classifier: Intended Audience :: Developers
Classifier: Topic :: Education
Classifier: Topic :: System :: Shells
Classifier: License :: OSI Approved :: MIT License
Requires-Dist: canvasapi (==0.12.0)
Requires-Dist: cmd2 (==0.9.12)
Requires-Dist: tabulate (>=0.8.3)
Requires-Dist: tree-format (>=0.1.2)
Requires-Dist: html2text
Requires-Dist: colorama
Requires-Dist: pytz
Requires-Dist: tzlocal
Provides-Extra: dev
Requires-Dist: requests-mock ; extra == 'dev'
